machine_learner/__init__.py
machine_learner/machine_learner.py
machine_learner-10.0.2.dist-info/LICENSE
machine_learner-10.0.2.dist-info/METADATA
machine_learner-10.0.2.dist-info/WHEEL
machine_learner-10.0.2.dist-info/top_level.txt
machine_learner-10.0.2.dist-info/RECORD
