Metadata-Version: 2.1
Name: machine_learner
Version: 10.0.2
Summary: A comprehensive Python module for feature engineering, target computation, rolling window modeling, feature selection, and model evaluation, tailored for time-series forecasting and stock price analysis.
Home-page: https://github.com/megandevelops/machine_learner
Author: Megan Jameson
Author-email: Megan Jameson <meganjameson.zealand@gmail.com>
Project-URL: Homepage, https://github.com/megandevelops/machine_learner
Project-URL: Issues, https://github.com/megandevelops/machine_learner/issues
Classifier: Programming Language :: Python :: 3
Classifier: License :: OSI Approved :: The Unlicense (Unlicense)
Classifier: Operating System :: OS Independent
Requires-Python: >=3.11
License-File: LICENSE
